qadence2_platforms/__init__.py
qadence2_platforms/abstracts.py
qadence2_platforms/compiler.py
qadence2_platforms/backends/__init__.py
qadence2_platforms/backends/utils.py
qadence2_platforms/backends/_base_analog/__init__.py
qadence2_platforms/backends/_base_analog/device_settings.py
qadence2_platforms/backends/_base_analog/functions.py
qadence2_platforms/backends/_base_analog/interface.py
qadence2_platforms/backends/_base_analog/register.py
qadence2_platforms/backends/_base_analog/sequence.py
qadence2_platforms/backends/analog/__init__.py
qadence2_platforms/backends/analog/compiler.py
qadence2_platforms/backends/analog/device_settings.py
qadence2_platforms/backends/analog/functions.py
qadence2_platforms/backends/analog/interface.py
qadence2_platforms/backends/analog/register.py
qadence2_platforms/backends/analog/sequence.py
qadence2_platforms/backends/fresnel1/__init__.py
qadence2_platforms/backends/fresnel1/compiler.py
qadence2_platforms/backends/fresnel1/device_settings.py
qadence2_platforms/backends/fresnel1/functions.py
qadence2_platforms/backends/fresnel1/interface.py
qadence2_platforms/backends/fresnel1/register.py
qadence2_platforms/backends/fresnel1/sequence.py
qadence2_platforms/backends/pyqtorch/__init__.py
qadence2_platforms/backends/pyqtorch/compiler.py
qadence2_platforms/backends/pyqtorch/embedding.py
qadence2_platforms/backends/pyqtorch/functions.py
qadence2_platforms/backends/pyqtorch/interface.py
qadence2_platforms/backends/pyqtorch/register.py
qadence2_platforms/utils/__init__.py
qadence2_platforms/utils/backend_template.py
qadence2_platforms/utils/module_importer.py
qadence2_platforms/utils/templates/__init__.py
qadence2_platforms/utils/templates/compiler.py
qadence2_platforms/utils/templates/interface.py
qadence2_platforms-0.2.3.dist-info/METADATA
qadence2_platforms-0.2.3.dist-info/WHEEL
qadence2_platforms-0.2.3.dist-info/RECORD
