Metadata-Version: 2.4
Name: qadence2-platforms
Version: 0.2.3
Summary: Platform-dependent engines and model to execute compiled expressions with common set of methods.
Project-URL: Documentation, https://pqs.pages.pasqal.com/qadence2-platforms/
Project-URL: Issues, https://github.com/pasqal-io/qadence2-platforms/-/issues
Project-URL: Source, https://github.com/pasqal-io/qadence2-platforms
Author-email: Eduardo Maschio <eduardo.maschio@pasqal.com>, Kaonan Micadei <kaonan.micadei@pasqal.com>, Dominik Seitz <dominik.seitz@pasqal.com>, Pim Venderbosch <pim.venderbosch@pasqal.com>, João Moutinho <joao.moutinho@pasqal.com>
License: Apache 2.0
Keywords: quantum
Classifier: Development Status :: 4 - Beta
Classifier: Programming Language :: Python
Classifier: Programming Language :: Python :: 3.10
Classifier: Programming Language :: Python :: 3.11
Classifier: Programming Language :: Python :: 3.12
Classifier: Programming Language :: Python :: Implementation :: CPython
Classifier: Programming Language :: Python :: Implementation :: PyPy
Requires-Python: <3.13,>=3.10
Requires-Dist: pulser~=1.2.0
Requires-Dist: pyqtorch~=1.7.0
Requires-Dist: qadence2-ir~=0.2.0
Provides-Extra: extras
